pydgets/__init__.py
pydgets/cowsay.py
pydgets/widgets.py
pydgets-0.11.dist-info/LICENSE.txt
pydgets-0.11.dist-info/METADATA
pydgets-0.11.dist-info/WHEEL
pydgets-0.11.dist-info/top_level.txt
pydgets-0.11.dist-info/RECORD
