Metadata-Version: 2.1
Name: pydgets
Version: 0.11
Summary: Console widget library for Python 3
Home-page: https://pypi.org/project/pydgets/
Author: Jan Mach
Author-email: email@jan-mach.cz
License: MIT
Project-URL: Documentation, https://709.gitlab-pages.cesnet.cz/mentat/pydgets/master/html/manual.html
Project-URL: Source, https://gitlab.cesnet.cz/709/mentat/pydgets
Project-URL: Tracker, https://gitlab.cesnet.cz/709/mentat/pydgets/-/issues
Keywords: library console widgets
Classifier: Development Status :: 3 - Alpha
Classifier: License :: OSI Approved :: MIT License
Classifier: Programming Language :: Python :: 3 :: Only
Classifier: Environment :: Console
License-File: LICENSE.txt
